{
   "رجع" :
   {
     "FUTURE":
     {
        "She": "ترجع",
        "He": "يرجع",
        "We": "نرجع",
        "I_F": "أرجع",
        "I_M": "أرجع"
     },
     "PAST":
     {
        "She": "رجعت",
        "He": "رجع",
        "We": "رجعنا",
        "I_F": "رجعت",
        "I_M": "رجعت"
     }
   },
   "هرب" :
   {
     "FUTURE":
     {
        "She": "تهرب",
        "He": "يهرب",
        "We": "نهرب",
        "I_F": "أهرب",
        "I_M": "أهرب"
     },
     "PAST":
     {
        "She": "هربت",
        "He": "هرب",
        "We": "هربنا",
        "I_F": "هربت",
        "I_M": "هربت"
     }
   }
}